{
  "protocol_version" : "0.0.6",
  "configuration" : {
    "version" : "(6.12.0.82) (2020-02/109b4b6f445)",
    "tlc" : "normal",
    "sigsgev" : "altstack",
    "notifications" : "kqueue",
    "architecture" : "amd64",
    "disabled_features" : "none",
    "smallconfig" : "disabled",
    "bigarrays" : "disabled",
    "softdebug" : "enabled",
    "interpreter" : "enabled",
    "llvm_support" : "0",
    "suspend" : "hybrid"
  },
  "memory" : {
    "Resident Size" : "160722944",
    "Virtual Size" : "5879328768",
    "minor_gc_time" : "0",
    "major_gc_time" : "0",
    "minor_gc_count" : "0",
    "major_gc_count" : "0",
    "major_gc_time_concurrent" : "0"
 },
  "threads" : [
 {
    "is_managed" : true,
    "offset_free_hash" : "0x11a6748113",
    "offset_rich_hash" : "0x11a6748628",
    "crashed" : true,
    "native_thread_id" : "0x700011d96000",
    "thread_info_addr" : "0x7f9d92473600",
    "thread_name" : "tid_6903",
    "ctx" : {
      "IP" : "0x7fff6804333a",
      "SP" : "0x700011d8eba8",
      "BP" : "0x700011d8ebd0"
  },
    "managed_frames" : [
  {
      "is_managed" : "false",
      "native_address" : "unregistered"
   }
,
  {
      "is_managed" : "true",
      "guid" : "FF24FA5F-206D-4C95-B527-639FAE9F9C06",
      "token" : "0x00000",
      "native_offset" : "0x0",
      "filename" : "mscorlib.dll",
      "sizeofimage" : "0x472000",
      "timestamp" : "0xbea10051",
      "il_offset" : "0x00000"
   }
,
  {
      "is_managed" : "true",
      "guid" : "FF24FA5F-206D-4C95-B527-639FAE9F9C06",
      "token" : "0x00000",
      "native_offset" : "0x0",
      "filename" : "mscorlib.dll",
      "sizeofimage" : "0x472000",
      "timestamp" : "0xbea10051",
      "il_offset" : "0x00015"
   }
,
  {
      "is_managed" : "true",
      "guid" : "55D6BCA6-9BF0-40A7-A0CD-41C568F4ABAC",
      "token" : "0x6004287",
      "native_offset" : "0x0",
      "filename" : "System.dll",
      "sizeofimage" : "0x292000",
      "timestamp" : "0xc2ea3fe3",
      "il_offset" : "0x0026a"
   }
,
  {
      "is_managed" : "true",
      "guid" : "55D6BCA6-9BF0-40A7-A0CD-41C568F4ABAC",
      "token" : "0x6004487",
      "native_offset" : "0x0",
      "filename" : "System.dll",
      "sizeofimage" : "0x292000",
      "timestamp" : "0xc2ea3fe3",
      "il_offset" : "0x00043"
   }
,
  {
      "is_managed" : "true",
      "guid" : "FF24FA5F-206D-4C95-B527-639FAE9F9C06",
      "token" : "0x6001ed4",
      "native_offset" : "0x0",
      "filename" : "mscorlib.dll",
      "sizeofimage" : "0x472000",
      "timestamp" : "0xbea10051",
      "il_offset" : "0x00071"
   }
,
  {
      "is_managed" : "true",
      "guid" : "FF24FA5F-206D-4C95-B527-639FAE9F9C06",
      "token" : "0x6001ed2",
      "native_offset" : "0x0",
      "filename" : "mscorlib.dll",
      "sizeofimage" : "0x472000",
      "timestamp" : "0xbea10051",
      "il_offset" : "0x00000"
   }
,
  {
      "is_managed" : "true",
      "guid" : "FF24FA5F-206D-4C95-B527-639FAE9F9C06",
      "token" : "0x6001ed1",
      "native_offset" : "0x0",
      "filename" : "mscorlib.dll",
      "sizeofimage" : "0x472000",
      "timestamp" : "0xbea10051",
      "il_offset" : "0x0002b"
   }
,
  {
      "is_managed" : "true",
      "guid" : "55D6BCA6-9BF0-40A7-A0CD-41C568F4ABAC",
      "token" : "0x6004286",
      "native_offset" : "0x0",
      "filename" : "System.dll",
      "sizeofimage" : "0x292000",
      "timestamp" : "0xc2ea3fe3",
      "il_offset" : "0x00093"
   }
,
  {
      "is_managed" : "true",
      "guid" : "55D6BCA6-9BF0-40A7-A0CD-41C568F4ABAC",
      "token" : "0x00000",
      "native_offset" : "0x0",
      "filename" : "System.dll",
      "sizeofimage" : "0x292000",
      "timestamp" : "0xc2ea3fe3",
      "il_offset" : "0xffffffff"
   }
,
  {
      "is_managed" : "false",
      "native_address" : "unregistered"
   }
,
  {
      "is_managed" : "true",
      "guid" : "55D6BCA6-9BF0-40A7-A0CD-41C568F4ABAC",
      "token" : "0x00000",
      "native_offset" : "0x0",
      "filename" : "System.dll",
      "sizeofimage" : "0x292000",
      "timestamp" : "0xc2ea3fe3",
      "il_offset" : "0x00000"
   }
,
  {
      "is_managed" : "true",
      "guid" : "55D6BCA6-9BF0-40A7-A0CD-41C568F4ABAC",
      "token" : "0x600447f",
      "native_offset" : "0x0",
      "filename" : "System.dll",
      "sizeofimage" : "0x292000",
      "timestamp" : "0xc2ea3fe3",
      "il_offset" : "0x0003a"
   }
,
  {
      "is_managed" : "true",
      "guid" : "FF24FA5F-206D-4C95-B527-639FAE9F9C06",
      "token" : "0x6001f2c",
      "native_offset" : "0x0",
      "filename" : "mscorlib.dll",
      "sizeofimage" : "0x472000",
      "timestamp" : "0xbea10051",
      "il_offset" : "0x00025"
   }
,
  {
      "is_managed" : "true",
      "guid" : "FF24FA5F-206D-4C95-B527-639FAE9F9C06",
      "token" : "0x6001ed4",
      "native_offset" : "0x0",
      "filename" : "mscorlib.dll",
      "sizeofimage" : "0x472000",
      "timestamp" : "0xbea10051",
      "il_offset" : "0x00071"
   }
,
  {
      "is_managed" : "true",
      "guid" : "FF24FA5F-206D-4C95-B527-639FAE9F9C06",
      "token" : "0x6001ed2",
      "native_offset" : "0x0",
      "filename" : "mscorlib.dll",
      "sizeofimage" : "0x472000",
      "timestamp" : "0xbea10051",
      "il_offset" : "0x00000"
   }
,
  {
      "is_managed" : "true",
      "guid" : "FF24FA5F-206D-4C95-B527-639FAE9F9C06",
      "token" : "0x6001ed1",
      "native_offset" : "0x0",
      "filename" : "mscorlib.dll",
      "sizeofimage" : "0x472000",
      "timestamp" : "0xbea10051",
      "il_offset" : "0x0002b"
   }
,
  {
      "is_managed" : "true",
      "guid" : "FF24FA5F-206D-4C95-B527-639FAE9F9C06",
      "token" : "0x00000",
      "native_offset" : "0x0",
      "filename" : "mscorlib.dll",
      "sizeofimage" : "0x472000",
      "timestamp" : "0xbea10051",
      "il_offset" : "0x0002a"
   }

  ],
  "unmanaged_frames" : [
 {
    "is_managed" : "false",
    "native_address" : "0x10cf84116",
    "native_offset" : "0x00000"
  }
,
 {
    "is_managed" : "false",
    "native_address" : "0x10d11f1f5",
    "native_offset" : "0x00000"
  }
,
 {
    "is_managed" : "false",
    "native_address" : "0x10d11f86a",
    "native_offset" : "0x00000"
  }
,
 {
    "is_managed" : "false",
    "native_address" : "0x10cff11b7",
    "native_offset" : "0x00000"
  }
,
 {
    "is_managed" : "false",
    "native_address" : "0x10cf88dc5",
    "native_offset" : "0x00000"
  }
,
 {
    "is_managed" : "false",
    "native_address" : "0x10cff04af",
    "native_offset" : "0x00000"
  }
,
 {
    "is_managed" : "false",
    "native_address" : "0x7fff680f45fd",
    "native_offset" : "0x00000"
  }
,
 {
    "is_managed" : "false",
    "native_address" : "unregistered"
  }
,
 {
    "is_managed" : "false",
    "native_address" : "0x7fff67fca808",
    "native_offset" : "0x00000"
  }
,
 {
    "is_managed" : "false",
    "native_address" : "0x10d1dcff7",
    "native_offset" : "0x00000"
  }
,
 {
    "is_managed" : "false",
    "native_address" : "0x10d1bde7f",
    "native_offset" : "0x00000"
  }
,
 {
    "is_managed" : "false",
    "native_address" : "0x10d1dd48e",
    "native_offset" : "0x00000"
  }
,
 {
    "is_managed" : "false",
    "native_address" : "0x10d1dd60f",
    "native_offset" : "0x00000"
  }
,
 {
    "is_managed" : "false",
    "native_address" : "0x10d1dd64a",
    "native_offset" : "0x00000"
  }
,
 {
    "is_managed" : "false",
    "native_address" : "0x10d1d1e1e",
    "native_offset" : "0x00000"
  }
,
 {
    "is_managed" : "false",
    "native_address" : "0x10d119781",
    "native_offset" : "0x00000"
  }
,
 {
    "is_managed" : "false",
    "native_address" : "0x10d1203dd",
    "native_offset" : "0x00000"
  }
,
 {
    "is_managed" : "false",
    "native_address" : "0x10d11e04c",
    "native_offset" : "0x00000"
  }
,
 {
    "is_managed" : "true",
    "guid" : "FF24FA5F-206D-4C95-B527-639FAE9F9C06",
    "token" : "0x00000",
    "native_offset" : "0x0",
    "filename" : "mscorlib.dll",
    "sizeofimage" : "0x472000",
    "timestamp" : "0xbea10051",
    "il_offset" : "0x00000"
  }
,
 {
    "is_managed" : "true",
    "guid" : "FF24FA5F-206D-4C95-B527-639FAE9F9C06",
    "token" : "0x00000",
    "native_offset" : "0x0",
    "filename" : "mscorlib.dll",
    "sizeofimage" : "0x472000",
    "timestamp" : "0xbea10051",
    "il_offset" : "0x00000"
  }
,
 {
    "is_managed" : "true",
    "guid" : "55D6BCA6-9BF0-40A7-A0CD-41C568F4ABAC",
    "token" : "0x6004287",
    "native_offset" : "0x0",
    "filename" : "System.dll",
    "sizeofimage" : "0x292000",
    "timestamp" : "0xc2ea3fe3",
    "il_offset" : "0x00000"
  }
,
 {
    "is_managed" : "true",
    "guid" : "55D6BCA6-9BF0-40A7-A0CD-41C568F4ABAC",
    "token" : "0x6004487",
    "native_offset" : "0x0",
    "filename" : "System.dll",
    "sizeofimage" : "0x292000",
    "timestamp" : "0xc2ea3fe3",
    "il_offset" : "0x00000"
  }
,
 {
    "is_managed" : "true",
    "guid" : "FF24FA5F-206D-4C95-B527-639FAE9F9C06",
    "token" : "0x6001ed4",
    "native_offset" : "0x0",
    "filename" : "mscorlib.dll",
    "sizeofimage" : "0x472000",
    "timestamp" : "0xbea10051",
    "il_offset" : "0x00000"
  }
,
 {
    "is_managed" : "true",
    "guid" : "FF24FA5F-206D-4C95-B527-639FAE9F9C06",
    "token" : "0x6001ed2",
    "native_offset" : "0x0",
    "filename" : "mscorlib.dll",
    "sizeofimage" : "0x472000",
    "timestamp" : "0xbea10051",
    "il_offset" : "0x00000"
  }
,
 {
    "is_managed" : "true",
    "guid" : "55D6BCA6-9BF0-40A7-A0CD-41C568F4ABAC",
    "token" : "0x00000",
    "native_offset" : "0x0",
    "filename" : "System.dll",
    "sizeofimage" : "0x292000",
    "timestamp" : "0xc2ea3fe3",
    "il_offset" : "0x00000"
  }
,
 {
    "is_managed" : "false",
    "native_address" : "0x7fff2f582993",
    "native_offset" : "0x00000"
  }
,
 {
    "is_managed" : "false",
    "native_address" : "0x7fff2f581dfe",
    "native_offset" : "0x00000"
  }
,
 {
    "is_managed" : "false",
    "native_address" : "0x7fff2f581cf7",
    "native_offset" : "0x00000"
  }
,
 {
    "is_managed" : "false",
    "native_address" : "0x7fff2f58492b",
    "native_offset" : "0x00000"
  }
,
 {
    "is_managed" : "false",
    "native_address" : "0x7fff2de93b05",
    "native_offset" : "0x00000"
  }
,
 {
    "is_managed" : "false",
    "native_address" : "0x7fff2de65304",
    "native_offset" : "0x00000"
  }
,
 {
    "is_managed" : "false",
    "native_address" : "0x7fff2de65250",
    "native_offset" : "0x00000"
  }
,
 {
    "is_managed" : "false",
    "native_address" : "0x7fff2de63d79",
    "native_offset" : "0x00000"
  }
,
 {
    "is_managed" : "false",
    "native_address" : "0x7fff2de62e3e",
    "native_offset" : "0x00000"
  }
,
 {
    "is_managed" : "false",
    "native_address" : "0x7fff2deeb489",
    "native_offset" : "0x00000"
  }
,
 {
    "is_managed" : "false",
    "native_address" : "0x10fe4afcc",
    "native_offset" : "0x00000"
  }
,
 {
    "is_managed" : "true",
    "guid" : "55D6BCA6-9BF0-40A7-A0CD-41C568F4ABAC",
    "token" : "0x00000",
    "native_offset" : "0x0",
    "filename" : "System.dll",
    "sizeofimage" : "0x292000",
    "timestamp" : "0xc2ea3fe3",
    "il_offset" : "0x00000"
  }
,
 {
    "is_managed" : "true",
    "guid" : "55D6BCA6-9BF0-40A7-A0CD-41C568F4ABAC",
    "token" : "0x600447f",
    "native_offset" : "0x0",
    "filename" : "System.dll",
    "sizeofimage" : "0x292000",
    "timestamp" : "0xc2ea3fe3",
    "il_offset" : "0x00000"
  }
,
 {
    "is_managed" : "true",
    "guid" : "FF24FA5F-206D-4C95-B527-639FAE9F9C06",
    "token" : "0x6001f2c",
    "native_offset" : "0x0",
    "filename" : "mscorlib.dll",
    "sizeofimage" : "0x472000",
    "timestamp" : "0xbea10051",
    "il_offset" : "0x00000"
  }
,
 {
    "is_managed" : "true",
    "guid" : "FF24FA5F-206D-4C95-B527-639FAE9F9C06",
    "token" : "0x6001ed2",
    "native_offset" : "0x0",
    "filename" : "mscorlib.dll",
    "sizeofimage" : "0x472000",
    "timestamp" : "0xbea10051",
    "il_offset" : "0x00000"
  }
,
 {
    "is_managed" : "false",
    "native_address" : "0x10cee6122",
    "native_offset" : "0x00000"
  }
,
 {
    "is_managed" : "false",
    "native_address" : "0x10d0f5047",
    "native_offset" : "0x00000"
  }
,
 {
    "is_managed" : "false",
    "native_address" : "0x10d0fb8f0",
    "native_offset" : "0x00000"
  }
,
 {
    "is_managed" : "false",
    "native_address" : "0x10d11fe7d",
    "native_offset" : "0x00000"
  }
,
 {
    "is_managed" : "false",
    "native_address" : "0x7fff68100109",
    "native_offset" : "0x00000"
  }
,
 {
    "is_managed" : "false",
    "native_address" : "0x7fff680fbb8b",
    "native_offset" : "0x00000"
  }

 ]
},
{
  "is_managed" : false,
  "offset_free_hash" : "0x0",
  "offset_rich_hash" : "0x0",
  "crashed" : false,
  "native_thread_id" : "0x70000f20e000",
  "thread_info_addr" : "0x7f9d9100f400",
  "thread_name" : "Finalizer",
  "ctx" : {
    "IP" : "0x7fff6803ce36",
    "SP" : "0x70000f20deb8",
    "BP" : "0x70000f20df00"
 },
  "unmanaged_frames" : [
 {
    "is_managed" : "false",
    "native_address" : "0x10cf84116",
    "native_offset" : "0x00000"
  }
,
 {
    "is_managed" : "false",
    "native_address" : "0x10d11f1f5",
    "native_offset" : "0x00000"
  }
,
 {
    "is_managed" : "false",
    "native_address" : "0x10d11ef27",
    "native_offset" : "0x00000"
  }
,
 {
    "is_managed" : "false",
    "native_address" : "0x10cff00f0",
    "native_offset" : "0x00000"
  }
,
 {
    "is_managed" : "false",
    "native_address" : "0x7fff680f45fd",
    "native_offset" : "0x00000"
  }
,
 {
    "is_managed" : "false",
    "native_address" : "unregistered"
  }
,
 {
    "is_managed" : "false",
    "native_address" : "0x10d11fe3d",
    "native_offset" : "0x00000"
  }
,
 {
    "is_managed" : "false",
    "native_address" : "0x7fff68100109",
    "native_offset" : "0x00000"
  }
,
 {
    "is_managed" : "false",
    "native_address" : "0x7fff680fbb8b",
    "native_offset" : "0x00000"
  }

 ]
},
{
  "is_managed" : false,
  "offset_free_hash" : "0x0",
  "offset_rich_hash" : "0x0",
  "crashed" : false,
  "native_thread_id" : "0x113dcfdc0",
  "thread_info_addr" : "0x7f9d93808200",
  "thread_name" : "tid_307",
  "ctx" : {
    "IP" : "0x7fff6803f882",
    "SP" : "0x7ffee2d2cc28",
    "BP" : "0x7ffee2d2ccc0"
 },
  "unmanaged_frames" : [
 {
    "is_managed" : "false",
    "native_address" : "0x10cf84116",
    "native_offset" : "0x00000"
  }
,
 {
    "is_managed" : "false",
    "native_address" : "0x10d11f1f5",
    "native_offset" : "0x00000"
  }
,
 {
    "is_managed" : "false",
    "native_address" : "0x10d11ef27",
    "native_offset" : "0x00000"
  }
,
 {
    "is_managed" : "false",
    "native_address" : "0x10cff00f0",
    "native_offset" : "0x00000"
  }
,
 {
    "is_managed" : "false",
    "native_address" : "0x7fff680f45fd",
    "native_offset" : "0x00000"
  }
,
 {
    "is_managed" : "false",
    "native_address" : "0x7ffee2d2c918",
    "native_offset" : "0x00000"
  }
,
 {
    "is_managed" : "false",
    "native_address" : "0x10d1b9f70",
    "native_offset" : "0x00000"
  }
,
 {
    "is_managed" : "false",
    "native_address" : "0x10d1d2051",
    "native_offset" : "0x00000"
  }
,
 {
    "is_managed" : "false",
    "native_address" : "0x10d11c134",
    "native_offset" : "0x00000"
  }
,
 {
    "is_managed" : "false",
    "native_address" : "0x10d11bf3a",
    "native_offset" : "0x00000"
  }
,
 {
    "is_managed" : "false",
    "native_address" : "0x10cf4984a",
    "native_offset" : "0x00000"
  }
,
 {
    "is_managed" : "false",
    "native_address" : "0x10ced53f9",
    "native_offset" : "0x00000"
  }
,
 {
    "is_managed" : "false",
    "native_address" : "0x7fff67efbcc9",
    "native_offset" : "0x00000"
  }

 ]
}
]
}